{
  "symbol": "ADI",
  "name": "Analog Devices, Inc.",
  "sector": "Technology",
  "industry": "Semiconductors",
  "market_cap": 138535387136,
  "enterprise_value": 141070237696,
  "pe_ratio": 62.181313,
  "forward_pe": 37.52321,
  "peg_ratio": null,
  "price_to_book": 4.0968,
  "dividend_yield": 1.43,
  "dividend_rate": 3.96,
  "payout_ratio": 0.8531,
  "trailing_annual_dividend": 3.96,
  "five_year_avg_dividend_yield": 1.71,
  "beta": 1.039,
  "fifty_two_week_high": 283.02,
  "fifty_two_week_low": 158.65,
  "fifty_day_average": 241.527,
  "two_hundred_day_average": 227.48735,
  "average_volume": 3507300,
  "average_volume_10d": 5241840,
  "shares_outstanding": 489654097,
  "float_shares": 487803205,
  "revenue": 11019707392,
  "profit_margin": 0.20575,
  "operating_margin": 0.30501,
  "roe": 0.06573,
  "roa": 0.03891,
  "debt_to_equity": 26.5,
  "current_ratio": 2.19,
  "quick_ratio": 1.568,
  "free_cash_flow": 3904020224,
  "operating_cash_flow": 4812201984,
  "earnings_growth": 0.661,
  "revenue_growth": 0.259,
  "snapshot_date": "2025-12-05T10:50:35.798188"
}