{
  "symbol": "BDX",
  "name": "Becton, Dickinson and Company",
  "sector": "Healthcare",
  "industry": "Medical Instruments & Supplies",
  "market_cap": 55018139648,
  "enterprise_value": 73734668288,
  "pe_ratio": 32.92453,
  "forward_pe": 12.202797,
  "peg_ratio": null,
  "price_to_book": 2.1576629,
  "dividend_yield": 2.21,
  "dividend_rate": 4.2,
  "payout_ratio": 0.71480006,
  "trailing_annual_dividend": 4.16,
  "five_year_avg_dividend_yield": 1.54,
  "beta": 0.285,
  "fifty_two_week_high": 251.99,
  "fifty_two_week_low": 162.29,
  "fifty_day_average": 187.54,
  "two_hundred_day_average": 191.7473,
  "average_volume": 1989923,
  "average_volume_10d": 1876210,
  "shares_outstanding": 285418551,
  "float_shares": 284727838,
  "revenue": 21839998976,
  "profit_margin": 0.07683,
  "operating_margin": 0.17858,
  "roe": 0.06544,
  "roa": 0.041739997,
  "debt_to_equity": 78.85,
  "current_ratio": 1.113,
  "quick_ratio": 0.438,
  "free_cash_flow": 3604875008,
  "operating_cash_flow": 3430000128,
  "earnings_growth": 0.252,
  "revenue_growth": 0.083,
  "snapshot_date": "2025-12-03T18:59:53.630889"
}