{
  "symbol": "CHRW",
  "name": "C.H. Robinson Worldwide, Inc.",
  "sector": "Industrials",
  "industry": "Integrated Freight & Logistics",
  "market_cap": 18573527040,
  "enterprise_value": 19939108864,
  "pe_ratio": 31.761618,
  "forward_pe": 33.02941,
  "peg_ratio": null,
  "price_to_book": 10.025507,
  "dividend_yield": 1.59,
  "dividend_rate": 2.52,
  "payout_ratio": 0.50200003,
  "trailing_annual_dividend": 2.48,
  "five_year_avg_dividend_yield": 2.36,
  "beta": 0.906,
  "fifty_two_week_high": 162.79,
  "fifty_two_week_low": 84.68,
  "fifty_day_average": 141.8438,
  "two_hundred_day_average": 113.37055,
  "average_volume": 1639230,
  "average_volume_10d": 1354870,
  "shares_outstanding": 118137178,
  "float_shares": 117661085,
  "revenue": 16504784896,
  "profit_margin": 0.03636,
  "operating_margin": 0.05578,
  "roe": 0.34318,
  "roa": 0.095790006,
  "debt_to_equity": 80.904,
  "current_ratio": 1.585,
  "quick_ratio": 1.516,
  "free_cash_flow": 741496256,
  "operating_cash_flow": 877035008,
  "earnings_growth": 0.675,
  "revenue_growth": -0.109,
  "snapshot_date": "2025-12-05T19:27:58.484149"
}